yuritasks/__init__.py
yuritasks/_assets.py
yuritasks/_environment.py
yuritasks/_tasker.py
yuritasks-0.0.1.dist-info/LICENSE
yuritasks-0.0.1.dist-info/METADATA
yuritasks-0.0.1.dist-info/WHEEL
yuritasks-0.0.1.dist-info/top_level.txt
yuritasks-0.0.1.dist-info/RECORD
