Metadata-Version: 2.1
Name: yuritasks
Version: 0.0.1
Summary: Task automation tool, automate those boring and repetitive tasks.
Home-page: https://github.com/edo0xff/yuri
Author: edo0xff
Author-email: edo0xff@pronton.me
Keywords: Task automation,Tool
Classifier: Development Status :: 4 - Beta
Classifier: Environment :: Console
Classifier: Programming Language :: Python :: 3.10
Classifier: License :: OSI Approved :: MIT License
Classifier: Intended Audience :: Developers
Classifier: Topic :: Utilities
Classifier: Operating System :: OS Independent
License-File: LICENSE
Requires-Dist: colorama
